[
  {
    "_raw_file": "/home/runner/work/econ-paper-monitor/econ-paper-monitor/data/raw/rss/2026-06-23.json",
    "abstract": null,
    "abstract_zh": null,
    "accepted_date": null,
    "ai_tags": [],
    "authors": [
      "Yong Li",
      "Sushanta K. Mallick",
      "Nianling Wang",
      "Jun Yu",
      "Tao Zeng"
    ],
    "available_online": "2025-03-17",
    "china_relevance_status": "none",
    "date_confidence": "B",
    "date_source": "rss_description_online",
    "detected_at": "2026-06-23T10:36:31+00:00",
    "doi": null,
    "fields": [
      "econometrics"
    ],
    "id": "url:4f5879566e479bd1",
    "issue_date": null,
    "journal": "Journal of Econometrics",
    "journal_id": "journal-of-econometrics",
    "journal_short": "JoE",
    "pdf_url": null,
    "published_online": "2025-03-17",
    "publisher": "Elsevier",
    "raw_data": {
      "rss_feed_url": "https://rss.sciencedirect.com/publication/science/03044076"
    },
    "source": "rss",
    "source_issue": "Journal of Econometrics",
    "source_type": "journal",
    "source_url": "https://rss.sciencedirect.com/publication/science/03044076",
    "title": "Deviance Information Criterion for Bayesian model selection: Theoretical justification and applications",
    "title_zh": "贝叶斯模型选择的偏差信息准则：理论依据与应用",
    "translation_status": "title_translated",
    "url": "https://www.sciencedirect.com/science/article/pii/S0304407625000326?dgcid=rss_sd_all"
  }
]
