[
  {
    "_raw_file": "/home/runner/work/econ-paper-monitor/econ-paper-monitor/data/raw/rss/2026-06-23.json",
    "abstract": null,
    "abstract_zh": null,
    "accepted_date": null,
    "ai_tags": [],
    "authors": [
      "Mattia Bevilacqua",
      "Michael Ellington",
      "Rodrigo Hizmeri"
    ],
    "available_online": "2026-04-03",
    "china_relevance_status": "none",
    "date_confidence": "B",
    "date_source": "rss_description_online",
    "detected_at": "2026-06-23T10:36:31+00:00",
    "doi": "10.1016/j.jeconom.2026.106238",
    "fields": [
      "econometrics"
    ],
    "id": "url:818a81eeb5a84919",
    "issue_date": "2026-07-01",
    "journal": "Journal of Econometrics",
    "journal_id": "journal-of-econometrics",
    "journal_short": "JoE",
    "pdf_url": null,
    "published_online": "2026-04-03",
    "publisher": "Elsevier",
    "raw_data": {
      "rss_feed_url": "https://rss.sciencedirect.com/publication/science/03044076"
    },
    "source": "rss",
    "source_issue": "Journal of Econometrics",
    "source_type": "journal",
    "source_url": "https://rss.sciencedirect.com/publication/science/03044076",
    "title": "Testing for differences in high-frequency network connectedness from variance decompositions",
    "title_zh": "基于方差分解的高频网络连通性差异检验",
    "translation_status": "title_translated",
    "url": "https://www.sciencedirect.com/science/article/pii/S030440762600059X?dgcid=rss_sd_all"
  },
  {
    "abstract": null,
    "abstract_zh": null,
    "accepted_date": null,
    "ai_tags": [],
    "authors": [
      "Klas Rönnbäck",
      "Guillaume Daudin",
      "Gerhard de Kok",
      "David Richardson",
      "Miguel Geraldes Rodrigues"
    ],
    "available_online": "2026-04-03",
    "china_relevance_status": "none",
    "date_confidence": "B",
    "date_source": "rss_published",
    "detected_at": "2026-06-23T04:39:34+00:00",
    "doi": null,
    "fields": [
      "economic_history"
    ],
    "id": "url:876bd2ac9c0b59d2",
    "issue_date": null,
    "journal": "Economic History Review",
    "journal_id": "economic-history-review",
    "journal_short": "EHR",
    "pdf_url": null,
    "published_online": "2026-04-03",
    "publisher": "Wiley (Blackwell Publishing)",
    "raw_data": {
      "rss_feed_url": "https://onlinelibrary.wiley.com/action/showFeed?jc=14680289&type=etoc&feed=rss"
    },
    "source": "rss",
    "source_issue": null,
    "source_type": "journal",
    "source_url": "https://onlinelibrary.wiley.com/action/showFeed?jc=14680289&type=etoc&feed=rss",
    "title": "Benefitting from brutality? Profits of north‐western Europe's slave trade at the eve of the industrial revolution",
    "title_zh": "从残暴中获益？工业革命前夕西北欧奴隶贸易的利润",
    "translation_status": "title_translated",
    "url": "https://onlinelibrary.wiley.com/doi/10.1111/ehr.70115?af=R"
  },
  {
    "abstract": null,
    "abstract_zh": null,
    "accepted_date": null,
    "ai_tags": [],
    "authors": [
      "Caroline Hall",
      "Kaisa Kotakorpi",
      "Linus Liljeberg",
      "Jukka Pirttilä"
    ],
    "available_online": "2026-04-03",
    "china_relevance_status": "none",
    "date_confidence": "B",
    "date_source": "rss_published",
    "detected_at": "2026-06-23T04:39:25+00:00",
    "doi": null,
    "fields": [
      "general"
    ],
    "id": "url:63fa03de1d6ed31c",
    "issue_date": null,
    "journal": "Scandinavian Journal of Economics",
    "journal_id": "scandinavian-journal-of-economics",
    "journal_short": "SJE",
    "pdf_url": null,
    "published_online": "2026-04-03",
    "publisher": "Wiley (Blackwell Publishing)",
    "raw_data": {
      "rss_feed_url": "https://onlinelibrary.wiley.com/action/showFeed?jc=14679442&type=etoc&feed=rss"
    },
    "source": "rss",
    "source_issue": null,
    "source_type": "journal",
    "source_url": "https://onlinelibrary.wiley.com/action/showFeed?jc=14679442&type=etoc&feed=rss",
    "title": "Health effects of a youth labor market activation policy",
    "title_zh": "青年劳动力市场激活政策的健康效应",
    "translation_status": "title_translated",
    "url": "https://onlinelibrary.wiley.com/doi/10.1111/sjoe.70018?af=R"
  }
]
