[
  {
    "abstract": null,
    "abstract_zh": null,
    "accepted_date": null,
    "ai_tags": [],
    "authors": [
      "Karen Arcia",
      "Livia Cerini",
      "Stephan von Cramon‐Taubadel"
    ],
    "available_online": "2026-04-16",
    "china_relevance_status": "none",
    "date_confidence": "B",
    "date_source": "rss_published",
    "detected_at": "2026-06-23T04:39:52+00:00",
    "doi": null,
    "fields": [
      "agriculture_environment_resource"
    ],
    "id": "url:c8089ec7bf92a7dd",
    "issue_date": null,
    "journal": "Australian Journal of Agricultural and Resource Economics",
    "journal_id": "australian-journal-of-agricultural-and-resource-economics",
    "journal_short": "AJARE",
    "pdf_url": null,
    "published_online": "2026-04-16",
    "publisher": "Wiley (Blackwell Publishing)",
    "raw_data": {
      "rss_feed_url": "https://onlinelibrary.wiley.com/action/showFeed?jc=14678489&type=etoc&feed=rss"
    },
    "source": "rss",
    "source_issue": null,
    "source_type": "journal",
    "source_url": "https://onlinelibrary.wiley.com/action/showFeed?jc=14678489&type=etoc&feed=rss",
    "title": "Awareness–Action and Policy Acceptability in Mitigating Greenhouse Gas Emissions: Key Stakeholders in Germany's Cattle Dairy and Meat Chains",
    "title_zh": "减缓温室气体排放中的认知-行动与政策可接受性：德国奶牛及肉牛产业链关键利益相关者研究",
    "translation_status": "title_translated",
    "url": "https://onlinelibrary.wiley.com/doi/10.1111/1467-8489.70102?af=R"
  },
  {
    "abstract": null,
    "abstract_zh": null,
    "accepted_date": null,
    "ai_tags": [],
    "authors": [
      "VEASNA KHENG",
      "LEI PAN",
      "XIAODONG FAN"
    ],
    "available_online": "2026-04-16",
    "china_relevance_status": "none",
    "date_confidence": "B",
    "date_source": "rss_published",
    "detected_at": "2026-06-23T04:39:43+00:00",
    "doi": null,
    "fields": [
      "macroeconomics"
    ],
    "id": "url:f97006c769e34e50",
    "issue_date": null,
    "journal": "Journal of Money, Credit and Banking",
    "journal_id": "journal-of-money-credit-and-banking",
    "journal_short": "JMCB",
    "pdf_url": null,
    "published_online": "2026-04-16",
    "publisher": "Wiley (Blackwell Publishing)",
    "raw_data": {
      "rss_feed_url": "https://onlinelibrary.wiley.com/action/showFeed?jc=15384616&type=etoc&feed=rss"
    },
    "source": "rss",
    "source_issue": null,
    "source_type": "journal",
    "source_url": "https://onlinelibrary.wiley.com/action/showFeed?jc=15384616&type=etoc&feed=rss",
    "title": "The Role of Remittances and FDI for the Current Account: The Case of Cambodia",
    "title_zh": "汇款与外国直接投资对经常账户的作用：柬埔寨案例",
    "translation_status": "title_translated",
    "url": "https://onlinelibrary.wiley.com/doi/10.1111/jmcb.70049?af=R"
  },
  {
    "abstract": null,
    "abstract_zh": null,
    "accepted_date": null,
    "ai_tags": [],
    "authors": [
      "Alessandro Morico",
      "Ovidijus Stauskas"
    ],
    "available_online": "2026-04-16",
    "china_relevance_status": "none",
    "date_confidence": "B",
    "date_source": "rss_published",
    "detected_at": "2026-06-23T04:39:41+00:00",
    "doi": null,
    "fields": [
      "applied_empirical"
    ],
    "id": "url:751890aca32c63d3",
    "issue_date": null,
    "journal": "Journal of Applied Econometrics",
    "journal_id": "journal-of-applied-econometrics",
    "journal_short": "JAE",
    "pdf_url": null,
    "published_online": "2026-04-16",
    "publisher": "Wiley (John Wiley & Sons)",
    "raw_data": {
      "rss_feed_url": "https://onlinelibrary.wiley.com/action/showFeed?jc=10991255&type=etoc&feed=rss"
    },
    "source": "rss",
    "source_issue": null,
    "source_type": "journal",
    "source_url": "https://onlinelibrary.wiley.com/action/showFeed?jc=10991255&type=etoc&feed=rss",
    "title": "Robust Tests of Forecast Accuracy for Factor‐Augmented Regressions With an Application to the Novel EA‐MD‐QD Dataset",
    "title_zh": "因子增强回归预测准确性的稳健检验：基于新型EA-MD-QD数据集的应用",
    "translation_status": "title_translated",
    "url": "https://onlinelibrary.wiley.com/doi/10.1002/jae.70056?af=R"
  },
  {
    "abstract": null,
    "abstract_zh": null,
    "accepted_date": null,
    "ai_tags": [],
    "authors": [
      "Anthony Lepinteur",
      "Andrew E. Clark",
      "Conchita D'Ambrosio"
    ],
    "available_online": "2026-04-16",
    "china_relevance_status": "none",
    "date_confidence": "B",
    "date_source": "rss_published",
    "detected_at": "2026-06-23T04:39:25+00:00",
    "doi": null,
    "fields": [
      "general"
    ],
    "id": "url:97960fab1d22e4f9",
    "issue_date": null,
    "journal": "Scandinavian Journal of Economics",
    "journal_id": "scandinavian-journal-of-economics",
    "journal_short": "SJE",
    "pdf_url": null,
    "published_online": "2026-04-16",
    "publisher": "Wiley (Blackwell Publishing)",
    "raw_data": {
      "rss_feed_url": "https://onlinelibrary.wiley.com/action/showFeed?jc=14679442&type=etoc&feed=rss"
    },
    "source": "rss",
    "source_issue": null,
    "source_type": "journal",
    "source_url": "https://onlinelibrary.wiley.com/action/showFeed?jc=14679442&type=etoc&feed=rss",
    "title": "Unsettled: job insecurity reduces homeownership",
    "title_zh": "不稳定的：工作不安全感降低住房拥有率",
    "translation_status": "title_translated",
    "url": "https://onlinelibrary.wiley.com/doi/10.1111/sjoe.70023?af=R"
  }
]
